autogluon.mxnet-0.3.1-py3.7-nspkg.pth
autogluon/mxnet/__init__.py
autogluon/mxnet/loss.py
autogluon/mxnet/optimizer.py
autogluon/mxnet/version.py
autogluon/mxnet/scheduler/__init__.py
autogluon/mxnet/scheduler/rl_scheduler.py
autogluon/mxnet/task/__init__.py
autogluon/mxnet/task/dataset.py
autogluon/mxnet/task/utils.py
autogluon/mxnet/utils/__init__.py
autogluon/mxnet/utils/dataloader.py
autogluon/mxnet/utils/dataset.py
autogluon/mxnet/utils/mxutils.py
autogluon/mxnet/utils/openml_download.py
autogluon/mxnet/utils/pil_transforms.py
autogluon.mxnet-0.3.1.dist-info/LICENSE
autogluon.mxnet-0.3.1.dist-info/METADATA
autogluon.mxnet-0.3.1.dist-info/NOTICE
autogluon.mxnet-0.3.1.dist-info/WHEEL
autogluon.mxnet-0.3.1.dist-info/namespace_packages.txt
autogluon.mxnet-0.3.1.dist-info/top_level.txt
autogluon.mxnet-0.3.1.dist-info/zip-safe
autogluon.mxnet-0.3.1.dist-info/RECORD
