Metadata-Version: 2.1
Name: autogluon.mxnet
Version: 0.3.1
Summary: AutoML for Text, Image, and Tabular Data
Home-page: https://github.com/awslabs/autogluon
Author: AutoGluon Community
License: Apache-2.0
Project-URL: Documentation, https://auto.gluon.ai
Project-URL: Bug Reports, https://github.com/awslabs/autogluon/issues
Project-URL: Source, https://github.com/awslabs/autogluon/
Project-URL: Contribute!, https://github.com/awslabs/autogluon/blob/master/CONTRIBUTING.md
Platform: UNKNOWN
Classifier: Development Status :: 4 - Beta
Classifier: Intended Audience :: Education
Classifier: Intended Audience :: Developers
Classifier: Intended Audience :: Science/Research
Classifier: Intended Audience :: Customer Service
Classifier: Intended Audience :: Financial and Insurance Industry
Classifier: Intended Audience :: Healthcare Industry
Classifier: Intended Audience :: Telecommunications Industry
Classifier: License :: OSI Approved :: Apache Software License
Classifier: Operating System :: MacOS
Classifier: Operating System :: Microsoft :: Windows
Classifier: Operating System :: POSIX
Classifier: Operating System :: Unix
Classifier: Programming Language :: Python :: 3
Classifier: Programming Language :: Python :: 3.6
Classifier: Programming Language :: Python :: 3.7
Classifier: Topic :: Software Development
Classifier: Topic :: Scientific/Engineering :: Artificial Intelligence
Classifier: Topic :: Scientific/Engineering :: Information Analysis
Classifier: Topic :: Scientific/Engineering :: Image Recognition
Requires-Python: >=3.6, <3.9
Requires-Dist: numpy (<1.22,>=1.19)
Requires-Dist: pandas (<2.0,>=1.0.0)
Requires-Dist: scikit-learn (<0.25,>=0.23.2)
Requires-Dist: Pillow (<8.4.0,>=8.3.0)
Requires-Dist: matplotlib
Requires-Dist: autogluon.core (==0.3.1)
Requires-Dist: pytest
Requires-Dist: openml
